blynklib.py
blynktimer.py
blynklib-0.2.5.dist-info/LICENSE.txt
blynklib-0.2.5.dist-info/METADATA
blynklib-0.2.5.dist-info/WHEEL
blynklib-0.2.5.dist-info/top_level.txt
blynklib-0.2.5.dist-info/RECORD
