Metadata-Version: 2.1
Name: blynklib
Version: 0.2.5
Summary: Blynk Python/Micropython library
Home-page: https://github.com/blynkkk/lib-python
Author: Anton Morozenko
Author-email: antoha.ua@gmail.com
License: MIT
Platform: UNKNOWN
Classifier: Programming Language :: Python :: 2.7
Classifier: Programming Language :: Python :: 3
Classifier: License :: OSI Approved :: MIT License
Classifier: Operating System :: OS Independent
